boa/__init__.py
boa/builtins.py
boa/compiler.py
boa/util.py
boa/code/__init__.py
boa/code/action.py
boa/code/appcall.py
boa/code/ast_preprocess.py
boa/code/expression.py
boa/code/method.py
boa/code/module.py
boa/code/pyop.py
boa/code/pytoken.py
boa/code/vmtoken.py
boa/interop/BigInteger.py
boa/interop/SmartContract.py
boa/interop/VMOp.py
boa/interop/__init__.py
boa/interop/Ontology/Attribute.py
boa/interop/Ontology/Contract.py
boa/interop/Ontology/Header.py
boa/interop/Ontology/Native.py
boa/interop/Ontology/Runtime.py
boa/interop/Ontology/Transaction.py
boa/interop/Ontology/__init__.py
boa/interop/System/Action.py
boa/interop/System/App.py
boa/interop/System/Block.py
boa/interop/System/Blockchain.py
boa/interop/System/Contract.py
boa/interop/System/ExecutionEngine.py
boa/interop/System/Header.py
boa/interop/System/Runtime.py
boa/interop/System/Storage.py
boa/interop/System/StorageContext.py
boa/interop/System/Transaction.py
boa/interop/System/__init__.py
punica_neo_boa-0.4.9.dist-info/METADATA
punica_neo_boa-0.4.9.dist-info/RECORD
punica_neo_boa-0.4.9.dist-info/WHEEL
punica_neo_boa-0.4.9.dist-info/top_level.txt
