Metadata-Version: 2.1
Name: punica-neo-boa
Version: 0.4.9
Summary: A simplified Python compiler for the Neo Virtual Machine to support ontology-python-punica
Home-page: https://github.com/wdx7266/punica-neo-boa
Author: Thomas Saunders
Author-email: tasaunders@gmail.com
License: MIT
Keywords: compiler NEO .avm blockchain smartcontract development dApp
Platform: UNKNOWN
Classifier: Development Status :: 3 - Alpha
Classifier: Intended Audience :: Developers
Classifier: Topic :: Software Development :: Build Tools
Classifier: License :: OSI Approved :: MIT License
Classifier: Programming Language :: Python :: 3.6
Classifier: Programming Language :: Python :: 3.7
Requires-Python: >=3.6
Provides-Extra: test
Provides-Extra: dev
Requires-Dist: coz-bytecode (==0.5.1)
Requires-Dist: astor (>=0.6.2)
Requires-Dist: logzero (==1.5.0)
Requires-Dist: base58 (>=1.0.0)
Provides-Extra: dev
Requires-Dist: twine; extra == 'dev'
Requires-Dist: wheel; extra == 'dev'
Requires-Dist: sphinx; extra == 'dev'
Requires-Dist: autopep8; extra == 'dev'
Requires-Dist: pep8; extra == 'dev'
Requires-Dist: sphinx-rtd-theme; extra == 'dev'
Provides-Extra: test
Requires-Dist: coverage; extra == 'test'
